README.md
README.rst
setup.cfg
setup.py
eden_client_api/__init__.py
eden_client_api/api.py
eden_client_api/config.py
edenchain_client_sdk.egg-info/PKG-INFO
edenchain_client_sdk.egg-info/SOURCES.txt
edenchain_client_sdk.egg-info/dependency_links.txt
edenchain_client_sdk.egg-info/not-zip-safe
edenchain_client_sdk.egg-info/requires.txt
edenchain_client_sdk.egg-info/top_level.txt