Metadata-Version: 1.1
Name: edenchain-client-sdk
Version: 0.1.6
Summary: edenchain client sdk
Home-page: UNKNOWN
Author: Edenpartners
Author-email: tech@edenchain.io
License: MIT
Platform: UNKNOWN
Classifier: Development Status :: 3 - Alpha
Classifier: Intended Audience :: Developers
Classifier: Programming Language :: Python :: 3
Classifier: License :: OSI Approved :: MIT License
